<?xml version="1.0" encoding="utf-8"?>
<Heroes>
    <!-- venice 1 -->
	<Hero id="lord_venice_1_1" spouse="Hero.lord_venice_1_2" faction="Faction.clan_venice_1" text="{=WBl5hS0e}text......"/>
	<Hero id="lord_venice_1_2" spouse="Hero.lord_venice_1_1" faction="Faction.clan_venice_1"/>
	<Hero id="lord_venice_1_3" father="Hero.lord_venice_1_1" mother="Hero.lord_venice_1_2" faction="Faction.clan_venice_1"/>
	<Hero id="lord_venice_1_4" father="Hero.lord_venice_1_1" mother="Hero.lord_venice_1_2" faction="Faction.clan_venice_1"/>
	<Hero id="lord_venice_1_5" spouse="Hero.lord_venice_1_4" faction="Faction.clan_venice_1"/>
	<Hero id="lord_venice_1_6" spouse="Hero.lord_venice_1_7" faction="Faction.clan_venice_1"/>
	<Hero id="lord_venice_1_7" spouse="Hero.lord_venice_1_6" faction="Faction.clan_venice_1"/>
	<Hero id="lord_venice_1_8" father="Hero.lord_venice_1_6" faction="Faction.clan_venice_1"/>
	<!-- venice 2 -->
	<Hero id="lord_venice_2_1" spouse="Hero.lord_venice_2_2" faction="Faction.clan_venice_2"/>
	<Hero id="lord_venice_2_2" spouse="Hero.lord_venice_2_1" faction="Faction.clan_venice_2"/>
	<Hero id="lord_venice_2_3" father="Hero.lord_venice_2_1" mother="Hero.lord_venice_2_2" faction="Faction.clan_venice_2"/>
	<Hero id="lord_venice_2_4" father="Hero.lord_venice_2_1" mother="Hero.lord_venice_2_2" faction="Faction.clan_venice_2"/>
	<Hero id="lord_venice_2_5" father="Hero.lord_venice_2_1" mother="Hero.lord_venice_2_2" faction="Faction.clan_venice_2"/>
	<Hero id="lord_venice_2_6" father="Hero.lord_venice_2_1" mother="Hero.lord_venice_2_2" faction="Faction.clan_venice_2"/>
	<Hero id="lord_venice_2_7" faction="Faction.clan_venice_2"/>
	<Hero id="lord_venice_2_8" spouse="Hero.lord_venice_2_7" faction="Faction.clan_venice_2"/>
	<Hero id="lord_venice_2_9" faction="Faction.clan_venice_2"/>
	<Hero id="lord_venice_2_10" spouse="Hero.lord_venice_2_9" faction="Faction.clan_venice_2"/>
	<!-- venice 3 -->
	<Hero id="lord_venice_3_1" faction="Faction.clan_venice_3" text="{=04xAg0yN}text......"/>
	<Hero id="lord_venice_3_2" spouse="Hero.lord_venice_3_1" faction="Faction.clan_venice_3"/>
	<Hero id="lord_venice_3_3" father="Hero.lord_venice_3_1" mother="Hero.lord_venice_3_2" faction="Faction.clan_venice_3"/>
	<Hero id="lord_venice_3_4" father="Hero.lord_venice_3_1" mother="Hero.lord_venice_3_2" faction="Faction.clan_venice_3"/>
	<Hero id="lord_venice_3_5" father="Hero.lord_venice_3_1" mother="Hero.lord_venice_3_2" faction="Faction.clan_venice_3"/>
	<Hero id="lord_venice_3_6" faction="Faction.clan_venice_3"/>
	<Hero id="lord_venice_3_7" spouse="Hero.lord_venice_3_6" faction="Faction.clan_venice_3"/>
	<Hero id="lord_venice_3_8" father="Hero.lord_venice_3_6" mother="Hero.lord_venice_3_7" faction="Faction.clan_venice_3"/>
	<Hero id="lord_venice_3_9" father="Hero.lord_venice_3_6" mother="Hero.lord_venice_3_7" faction="Faction.clan_venice_3"/>
	<!-- venice 4 -->
	<Hero id="lord_venice_4_1" faction="Faction.clan_venice_4"/>
	<Hero id="lord_venice_4_2" faction="Faction.clan_venice_4"/>
	<Hero id="lord_venice_4_3" spouse="Hero.lord_venice_4_2" faction="Faction.clan_venice_4"/>
	<Hero id="lord_venice_4_4" faction="Faction.clan_venice_4" text="{=SeQ5dM4H}text......"/>
	<!-- venice 5 -->
	<Hero id="lord_venice_5_1" faction="Faction.clan_venice_5"/>
	<Hero id="lord_venice_5_2" spouse="Hero.lord_venice_5_1" faction="Faction.clan_venice_5"/>
	<Hero id="lord_venice_5_3" faction="Faction.clan_venice_5"/>
	<Hero id="lord_venice_5_4" faction="Faction.clan_venice_5"/>
	<!-- venice 6 -->
	<Hero id="lord_venice_6_1" faction="Faction.clan_venice_6"/>
	<Hero id="lord_venice_6_2" faction="Faction.clan_venice_6"/>
	<Hero id="lord_venice_6_3" spouse="Hero.lord_venice_6_2" faction="Faction.clan_venice_6"/>
	<Hero id="lord_venice_6_4" father="Hero.lord_venice_6_2" mother="Hero.lord_venice_6_3" faction="Faction.clan_venice_6"/>
	<!-- venice 7 -->
	<Hero id="lord_venice_7_1" faction="Faction.clan_venice_7"/>
	<Hero id="lord_venice_7_2" faction="Faction.clan_venice_7"/>
	<Hero id="lord_venice_7_3" faction="Faction.clan_venice_7"/>
	<!-- venice 8 -->
	<Hero id="lord_venice_8_1" spouse="Hero.lord_venice_8_2" faction="Faction.clan_venice_8"/>
	<Hero id="lord_venice_8_2" spouse="Hero.lord_venice_8_1" faction="Faction.clan_venice_8"/>
	<Hero id="lord_venice_8_3" father="Hero.lord_venice_8_1" mother="Hero.lord_venice_8_2" faction="Faction.clan_venice_8"/>
	<Hero id="lord_venice_8_4" father="Hero.lord_venice_8_1" mother="Hero.lord_venice_8_2" faction="Faction.clan_venice_8"/>
	<Hero id="lord_venice_8_5" spouse="Hero.lord_venice_8_6" faction="Faction.clan_venice_8"/>
	<Hero id="lord_venice_8_6" spouse="Hero.lord_venice_8_5" faction="Faction.clan_venice_8"/>
	<!-- venice 9 -->
	<Hero id="lord_venice_9_1" faction="Faction.clan_venice_9"/>
	<Hero id="lord_venice_9_2" father="Hero.lord_venice_9_1" faction="Faction.clan_venice_9"/>
	<Hero id="lord_venice_9_3" father="Hero.lord_venice_9_1" faction="Faction.clan_venice_9"/>
</Heroes>